santali_textts/__init__.py
santali_textts/santali_textts.py
santali_textts-0.0.3.dist-info/LICENSE
santali_textts-0.0.3.dist-info/METADATA
santali_textts-0.0.3.dist-info/WHEEL
santali_textts-0.0.3.dist-info/entry_points.txt
santali_textts-0.0.3.dist-info/top_level.txt
santali_textts-0.0.3.dist-info/RECORD
