Metadata-Version: 2.1
Name: santali_textts
Version: 0.0.3
Summary: Convert Olchiki text into speech (Beta version)
Author: Shivnath Kisku
Classifier: Programming Language :: Python :: 3
Classifier: License :: OSI Approved :: MIT License
Classifier: Operating System :: OS Independent
Requires-Python: >=3.6
License-File: LICENSE
